dashy/__init__.py
dashy/__main__.py
dashy/config.py
dashy/dashy.py
dashy/themes.py
dashy/utils.py
dashy/components/__init__.py
dashy/components/attributes.py
dashy/components/core.py
dashy/components/helpers.py
dashy/components/layout.py
dashy/components/navigation.py
dashy/components/slider.py
dashy/components/table.py
dashy/components/upload.py
dash_dashy-0.0.2.dist-info/LICENSE
dash_dashy-0.0.2.dist-info/METADATA
dash_dashy-0.0.2.dist-info/WHEEL
dash_dashy-0.0.2.dist-info/entry_points.txt
dash_dashy-0.0.2.dist-info/top_level.txt
dash_dashy-0.0.2.dist-info/RECORD
