Metadata-Version: 2.1
Name: dash-dashy
Version: 0.0.2
Summary: Easy-to-use data visualization framework
Author-email: Toni Axelsson <toniaxelsson@gmail.com>
License: MIT License (MIT)        
Project-URL: homepage, https://github.com/wynss/dashy
Keywords: visualization,web,data science
Classifier: License :: OSI Approved :: MIT License
Classifier: Programming Language :: Python
Classifier: Programming Language :: Python :: 3
Classifier: Programming Language :: Python :: 3.8
Classifier: Programming Language :: Python :: 3.9
Classifier: Programming Language :: Python :: 3.10
Requires-Python: >=3.9
License-File: LICENSE
Requires-Dist: dash (>=2.6.1)
Requires-Dist: dash-bootstrap-components (>=1.2.1)
Requires-Dist: libsass (>=0.21.0)
Requires-Dist: pandas (>=1.4.3)
Provides-Extra: dev
Requires-Dist: flake8 ; extra == 'dev'
Requires-Dist: pytest ; extra == 'dev'
Requires-Dist: black ; extra == 'dev'
Requires-Dist: bumpver ; extra == 'dev'
Requires-Dist: build ; extra == 'dev'
Requires-Dist: twine ; extra == 'dev'
